jsonquerylang/__init__.py
jsonquerylang/compile.py
jsonquerylang/functions.py
jsonquerylang/jsonquery.py
jsonquerylang/operators.py
jsonquerylang/parse.py
jsonquerylang/regexps.py
jsonquerylang/stringify.py
jsonquerylang/types.py
jsonquerylang/utils.py
jsonquerylang-2.1.0.dist-info/licenses/LICENSE.md
jsonquerylang-2.1.0.dist-info/METADATA
jsonquerylang-2.1.0.dist-info/WHEEL
jsonquerylang-2.1.0.dist-info/top_level.txt
jsonquerylang-2.1.0.dist-info/RECORD
